LICENSE.txt
MANIFEST.in
README.md
pyproject.toml
setup.cfg
setup.py
src/__init__.py
src/main_bb84.py
src/main_e91.py
src/main_quantum_solver.py
src/main_rsa_substitute.py
src/quantum_solver_library.egg-info/PKG-INFO
src/quantum_solver_library.egg-info/SOURCES.txt
src/quantum_solver_library.egg-info/dependency_links.txt
src/quantum_solver_library.egg-info/requires.txt
src/quantum_solver_library.egg-info/top_level.txt